setup.py
zotmer/__init__.py
zotmer/cli.py
zotmer.egg-info/PKG-INFO
zotmer.egg-info/SOURCES.txt
zotmer.egg-info/dependency_links.txt
zotmer.egg-info/entry_points.txt
zotmer.egg-info/not-zip-safe
zotmer.egg-info/requires.txt
zotmer.egg-info/top_level.txt
zotmer/commands/__init__.py
zotmer/commands/contigs.py
zotmer/commands/dist.py
zotmer/commands/dump.py
zotmer/commands/hist.py
zotmer/commands/info.py
zotmer/commands/jaccard.py
zotmer/commands/kmerize.py
zotmer/commands/ksnp.py
zotmer/commands/merge.py
zotmer/commands/mlst.py
zotmer/commands/project.py
zotmer/commands/sample.py
zotmer/commands/scan.py
zotmer/commands/spoligo.py
zotmer/commands/trim.py
zotmer/commands/vars.py
zotmer/library/__init__.py
zotmer/library/merge.py