Metadata-Version: 1.0
Name: zotmer
Version: 0.1
Summary: A python k-mer application workbench
Home-page: http://github.com/drtconway/zotmer
Author: Tom Conway
Author-email: drtomc@gmail.com
License: Apache2
Keywords: bioinformatics genomics pathogenomics
Platform: UNKNOWN
